<annotation>
	<folder>esteban</folder>
	<filename>344.jpg</filename>
	<path>C:\Users\57301\Desktop\fotos_peces\LM_IMAGES\esteban\D prosopotaenia 4.6 TL.jpg</path>
	<source>
		<database>Unknown</database>
	</source>
	<size>
		<width>640</width>
		<height>428</height>
		<depth>3</depth>
	</size>
	<segmented>0</segmented>
	<object>
		<name>Boca</name>
		<pose>Unspecified</pose>
		<truncated>0</truncated>
		<difficult>0</difficult>
		<bndbox>
			<xmin>10</xmin>
			<ymin>190</ymin>
			<xmax>40</xmax>
			<ymax>250</ymax>
		</bndbox>
	</object>
	<object>
		<name>Ojo</name>
		<pose>Unspecified</pose>
		<truncated>0</truncated>
		<difficult>0</difficult>
		<bndbox>
			<xmin>45</xmin>
			<ymin>158</ymin>
			<xmax>111</xmax>
			<ymax>210</ymax>
		</bndbox>
	</object>
	<object>
		<name>cola</name>
		<pose>Unspecified</pose>
		<truncated>0</truncated>
		<difficult>0</difficult>
		<bndbox>
			<xmin>448</xmin>
			<ymin>123</ymin>
			<xmax>627</xmax>
			<ymax>313</ymax>
		</bndbox>
	</object>
	<object>
		<name>aleta</name>
		<pose>Unspecified</pose>
		<truncated>0</truncated>
		<difficult>0</difficult>
		<bndbox>
			<xmin>148</xmin>
			<ymin>180</ymin>
			<xmax>311</xmax>
			<ymax>281</ymax>
		</bndbox>
	</object>
	<object>
		<name>cuerpo</name>
		<pose>Unspecified</pose>
		<truncated>0</truncated>
		<difficult>0</difficult>
		<bndbox>
			<xmin>10</xmin>
			<ymin>24</ymin>
			<xmax>637</xmax>
			<ymax>411</ymax>
		</bndbox>
	</object>
</annotation>