<annotation>
	<folder>esteban</folder>
	<filename>430.jpg</filename>
	<path>C:\Users\57301\Desktop\fotos_peces\LM_IMAGES\esteban\P leucozonus 4.8 SL.jpg</path>
	<source>
		<database>Unknown</database>
	</source>
	<size>
		<width>537</width>
		<height>360</height>
		<depth>3</depth>
	</size>
	<segmented>0</segmented>
	<object>
		<name>Boca</name>
		<pose>Unspecified</pose>
		<truncated>0</truncated>
		<difficult>0</difficult>
		<bndbox>
			<xmin>13</xmin>
			<ymin>141</ymin>
			<xmax>41</xmax>
			<ymax>166</ymax>
		</bndbox>
	</object>
	<object>
		<name>Ojo</name>
		<pose>Unspecified</pose>
		<truncated>0</truncated>
		<difficult>0</difficult>
		<bndbox>
			<xmin>37</xmin>
			<ymin>110</ymin>
			<xmax>75</xmax>
			<ymax>148</ymax>
		</bndbox>
	</object>
	<object>
		<name>cola</name>
		<pose>Unspecified</pose>
		<truncated>0</truncated>
		<difficult>0</difficult>
		<bndbox>
			<xmin>359</xmin>
			<ymin>109</ymin>
			<xmax>520</xmax>
			<ymax>231</ymax>
		</bndbox>
	</object>
	<object>
		<name>aleta</name>
		<pose>Unspecified</pose>
		<truncated>0</truncated>
		<difficult>0</difficult>
		<bndbox>
			<xmin>104</xmin>
			<ymin>147</ymin>
			<xmax>244</xmax>
			<ymax>225</ymax>
		</bndbox>
	</object>
	<object>
		<name>cuerpo</name>
		<pose>Unspecified</pose>
		<truncated>0</truncated>
		<difficult>0</difficult>
		<bndbox>
			<xmin>10</xmin>
			<ymin>19</ymin>
			<xmax>525</xmax>
			<ymax>354</ymax>
		</bndbox>
	</object>
</annotation>