<annotation>
	<folder>tomas</folder>
	<filename>90.jpg</filename>
	<path>C:\Users\Asus\Desktop\fotos_peces\LM_IMAGES\tomas\S canaliculatus 8.7 SL.jpg</path>
	<source>
		<database>Unknown</database>
	</source>
	<size>
		<width>640</width>
		<height>373</height>
		<depth>3</depth>
	</size>
	<segmented>0</segmented>
	<object>
		<name>Boca</name>
		<pose>Unspecified</pose>
		<truncated>0</truncated>
		<difficult>0</difficult>
		<bndbox>
			<xmin>28</xmin>
			<ymin>178</ymin>
			<xmax>57</xmax>
			<ymax>216</ymax>
		</bndbox>
	</object>
	<object>
		<name>Ojo</name>
		<pose>Unspecified</pose>
		<truncated>0</truncated>
		<difficult>0</difficult>
		<bndbox>
			<xmin>68</xmin>
			<ymin>144</ymin>
			<xmax>110</xmax>
			<ymax>183</ymax>
		</bndbox>
	</object>
	<object>
		<name>cola</name>
		<pose>Unspecified</pose>
		<truncated>0</truncated>
		<difficult>0</difficult>
		<bndbox>
			<xmin>508</xmin>
			<ymin>130</ymin>
			<xmax>613</xmax>
			<ymax>270</ymax>
		</bndbox>
	</object>
	<object>
		<name>aleta</name>
		<pose>Unspecified</pose>
		<truncated>0</truncated>
		<difficult>0</difficult>
		<bndbox>
			<xmin>149</xmin>
			<ymin>186</ymin>
			<xmax>222</xmax>
			<ymax>253</ymax>
		</bndbox>
	</object>
	<object>
		<name>cuerpo</name>
		<pose>Unspecified</pose>
		<truncated>0</truncated>
		<difficult>0</difficult>
		<bndbox>
			<xmin>28</xmin>
			<ymin>31</ymin>
			<xmax>607</xmax>
			<ymax>342</ymax>
		</bndbox>
	</object>
</annotation>